graphql_compiler/__init__.py
graphql_compiler/ast_manipulation.py
graphql_compiler/debugging_utils.py
graphql_compiler/exceptions.py
graphql_compiler/schema.py
graphql_compiler/tool.py
graphql_compiler/compiler/__init__.py
graphql_compiler/compiler/blocks.py
graphql_compiler/compiler/common.py
graphql_compiler/compiler/compiler_entities.py
graphql_compiler/compiler/compiler_frontend.py
graphql_compiler/compiler/context_helpers.py
graphql_compiler/compiler/cypher_query.py
graphql_compiler/compiler/directive_helpers.py
graphql_compiler/compiler/emit_cypher.py
graphql_compiler/compiler/emit_gremlin.py
graphql_compiler/compiler/emit_match.py
graphql_compiler/compiler/emit_sql.py
graphql_compiler/compiler/expressions.py
graphql_compiler/compiler/filters.py
graphql_compiler/compiler/helpers.py
graphql_compiler/compiler/ir_sanity_checks.py
graphql_compiler/compiler/match_query.py
graphql_compiler/compiler/metadata.py
graphql_compiler/compiler/sql_context_helpers.py
graphql_compiler/compiler/ir_lowering_common/__init__.py
graphql_compiler/compiler/ir_lowering_common/common.py
graphql_compiler/compiler/ir_lowering_common/location_renaming.py
graphql_compiler/compiler/ir_lowering_cypher/__init__.py
graphql_compiler/compiler/ir_lowering_cypher/ir_lowering.py
graphql_compiler/compiler/ir_lowering_gremlin/__init__.py
graphql_compiler/compiler/ir_lowering_gremlin/ir_lowering.py
graphql_compiler/compiler/ir_lowering_match/__init__.py
graphql_compiler/compiler/ir_lowering_match/between_lowering.py
graphql_compiler/compiler/ir_lowering_match/ir_lowering.py
graphql_compiler/compiler/ir_lowering_match/optional_traversal.py
graphql_compiler/compiler/ir_lowering_match/utils.py
graphql_compiler/compiler/ir_lowering_sql/__init__.py
graphql_compiler/compiler/ir_lowering_sql/constants.py
graphql_compiler/compiler/ir_lowering_sql/metadata.py
graphql_compiler/compiler/ir_lowering_sql/sql_tree.py
graphql_compiler/compiler/workarounds/__init__.py
graphql_compiler-1.11.0.dist-info/AUTHORS.md
graphql_compiler-1.11.0.dist-info/LICENSE.txt
graphql_compiler-1.11.0.dist-info/METADATA
graphql_compiler-1.11.0.dist-info/WHEEL
graphql_compiler-1.11.0.dist-info/top_level.txt
graphql_compiler-1.11.0.dist-info/RECORD
