Metadata-Version: 2.1
Name: graphql-compiler
Version: 1.11.0
Summary: Turn complex GraphQL queries into optimized database queries.
Home-page: https://github.com/kensho-technologies/graphql-compiler
Author: Kensho Technologies, LLC.
Author-email: graphql-compiler-maintainer@kensho.com
License: Apache 2.0
Keywords: graphql database compiler orientdb
Platform: UNKNOWN
Classifier: Development Status :: 5 - Production/Stable
Classifier: Topic :: Database :: Front-Ends
Classifier: Topic :: Software Development :: Compilers
Classifier: Intended Audience :: Developers
Classifier: License :: OSI Approved :: Apache Software License
Classifier: Programming Language :: Python :: 2
Classifier: Programming Language :: Python :: 2.7
Classifier: Programming Language :: Python :: 3
Classifier: Programming Language :: Python :: 3.5
Classifier: Programming Language :: Python :: 3.6
Classifier: Programming Language :: Python :: 3.7
Requires-Python: >=2.7,!=3.0.*,!=3.1.*,!=3.2.*
Requires-Dist: arrow (<1,>=0.7.0)
Requires-Dist: funcy (<2,>=1.6)
Requires-Dist: graphql-core (<3,>=2.1)
Requires-Dist: pytz (>=2016.10)
Requires-Dist: six (>=1.10.0)
Requires-Dist: sqlalchemy (<2,>=1.3.0)
